[{"statNm": "\uc591\ucc9c\ubb38\ud654\ud68c\uad00", "statId": "CU201001", "chgerId": "02", "chgerType": "02", "addr": "\uc11c\uc6b8\ud2b9\ubcc4\uc2dc \uc591\ucc9c\uad6c \ubaa9\ub3d9\uc11c\ub85c 367", "location": "\ub3c4\ub85c\uc606\uc9c0\uc0c1\uc8fc\ucc28\uc7a5", "lat": "37.5166513", "lng": "126.8633139", "useTime": "24\uc2dc\uac04 \uc774\uc6a9\uac00\ub2a5", "busiId": "CU", "bnm": "\uc528\uc5b4\uc2a4", "busiNm": "(\uc8fc)\uc528\uc5b4\uc2a4", "busiCall": "1522-2640", "stat": "9", "statUpdDt": "20220105195810", "lastTsdt": "20220105171520", "lastTedt": "20220105175550", "nowTsdt": "20220105171520", "powerType": null, "output": null, "method": null, "zcode": "11", "zscode": "11470", "kind": "A0", "kindDetail": "A004", "parkingFree": "N", "note": null, "limitYn": "Y", "limitDetail": "\uc2dc\uc124 \uc0c1\ud669\uc5d0 \ub530\ub77c \uc774\uc6a9\uc774 \uc81c\ud55c\ub420 \uc218 \uc788\uc74c", "delYn": "N", "delDetail": null}, {"statNm": "\uc591\ucc9c\ubb38\ud654\ud68c\uad00", "statId": "CU201001", "chgerId": "03", "chgerType": "02", "addr": "\uc11c\uc6b8\ud2b9\ubcc4\uc2dc \uc591\ucc9c\uad6c \ubaa9\ub3d9\uc11c\ub85c 367", "location": "\ub3c4\ub85c\uc606\uc9c0\uc0c1\uc8fc\ucc28\uc7a5", "lat": "37.5166513", "lng": "126.8633139", "useTime": "24\uc2dc\uac04 \uc774\uc6a9\uac00\ub2a5", "busiId": "CU", "bnm": "\uc528\uc5b4\uc2a4", "busiNm": "(\uc8fc)\uc528\uc5b4\uc2a4", "busiCall": "1522-2640", "stat": "9", "statUpdDt": "20220105201310", "lastTsdt": "20220105184954", "lastTedt": "20220105184954", "nowTsdt": "20220105184954", "powerType": null, "output": null, "method": "\ub2e8\ub3c5", "zcode": "11", "zscode": "11470", "kind": "A0", "kindDetail": "A004", "parkingFree": "N", "note": null, "limitYn": "Y", "limitDetail": "\uc2dc\uc124 \uc0c1\ud669\uc5d0 \ub530\ub77c \uc774\uc6a9\uc774 \uc81c\ud55c\ub420 \uc218 \uc788\uc74c", "delYn": "N", "delDetail": null}, {"statNm": "\uc591\ucc9c\ubb38\ud654\ud68c\uad00", "statId": "CU201001", "chgerId": "04", "chgerType": "02", "addr": "\uc11c\uc6b8\ud2b9\ubcc4\uc2dc \uc591\ucc9c\uad6c \ubaa9\ub3d9\uc11c\ub85c 367", "location": "\ub3c4\ub85c\uc606\uc9c0\uc0c1\uc8fc\ucc28\uc7a5", "lat": "37.5166513", "lng": "126.8633139", "useTime": "24\uc2dc\uac04 \uc774\uc6a9\uac00\ub2a5", "busiId": "CU", "bnm": "\uc528\uc5b4\uc2a4", "busiNm": "(\uc8fc)\uc528\uc5b4\uc2a4", "busiCall": "1522-2640", "stat": "9", "statUpdDt": "20220105201310", "lastTsdt": "20211231185911", "lastTedt": "20211231190240", "nowTsdt": "20211231185911", "powerType": null, "output": null, "method": "\ub2e8\ub3c5", "zcode": "11", "zscode": "11470", "kind": "A0", "kindDetail": "A004", "parkingFree": "N", "note": null, "limitYn": "Y", "limitDetail": "\uc2dc\uc124 \uc0c1\ud669\uc5d0 \ub530\ub77c \uc774\uc6a9\uc774 \uc81c\ud55c\ub420 \uc218 \uc788\uc74c", "delYn": "N", "delDetail": null}, {"statNm": "\uc591\ucc9c\ubb38\ud654\ud68c\uad00", "statId": "CU201001", "chgerId": "05", "chgerType": "02", "addr": "\uc11c\uc6b8\ud2b9\ubcc4\uc2dc \uc591\ucc9c\uad6c \ubaa9\ub3d9\uc11c\ub85c 367", "location": "\ub3c4\ub85c\uc606\uc9c0\uc0c1\uc8fc\ucc28\uc7a5", "lat": "37.5166513", "lng": "126.8633139", "useTime": "24\uc2dc\uac04 \uc774\uc6a9\uac00\ub2a5", "busiId": "CU", "bnm": "\uc528\uc5b4\uc2a4", "busiNm": "(\uc8fc)\uc528\uc5b4\uc2a4", "busiCall": "1522-2640", "stat": "9", "statUpdDt": "20220113115810", "lastTsdt": "20220106202407", "lastTedt": "20220107071757", "nowTsdt": "20220106202407", "powerType": null, "output": null, "method": null, "zcode": "11", "zscode": "11470", "kind": "A0", "kindDetail": "A004", "parkingFree": "N", "note": null, "limitYn": "Y", "limitDetail": "\uc2dc\uc124 \uc0c1\ud669\uc5d0 \ub530\ub77c \uc774\uc6a9\uc774 \uc81c\ud55c\ub420 \uc218 \uc788\uc74c", "delYn": "N", "delDetail": null}, {"statNm": "\uc591\ucc9c\ubb38\ud654\ud68c\uad00", "statId": "CU201001", "chgerId": "06", "chgerType": "02", "addr": "\uc11c\uc6b8\ud2b9\ubcc4\uc2dc \uc591\ucc9c\uad6c \ubaa9\ub3d9\uc11c\ub85c 367", "location": "\ub3c4\ub85c\uc606\uc9c0\uc0c1\uc8fc\ucc28\uc7a5", "lat": "37.5166513", "lng": "126.8633139", "useTime": "24\uc2dc\uac04 \uc774\uc6a9\uac00\ub2a5", "busiId": "CU", "bnm": "\uc528\uc5b4\uc2a4", "busiNm": "(\uc8fc)\uc528\uc5b4\uc2a4", "busiCall": "1522-2640", "stat": "9", "statUpdDt": "20220113115810", "lastTsdt": "20220106163137", "lastTedt": "20220107015849", "nowTsdt": "20220106163137", "powerType": null, "output": null, "method": null, "zcode": "11", "zscode": "11470", "kind": "A0", "kindDetail": "A004", "parkingFree": "N", "note": null, "limitYn": "Y", "limitDetail": "\uc2dc\uc124 \uc0c1\ud669\uc5d0 \ub530\ub77c \uc774\uc6a9\uc774 \uc81c\ud55c\ub420 \uc218 \uc788\uc74c", "delYn": "N", "delDetail": null}, {"statNm": "\uc591\ucc9c\ubb38\ud654\ud68c\uad00", "statId": "CU201001", "chgerId": "07", "chgerType": "02", "addr": "\uc11c\uc6b8\ud2b9\ubcc4\uc2dc \uc591\ucc9c\uad6c \ubaa9\ub3d9\uc11c\ub85c 367", "location": "\ub3c4\ub85c\uc606\uc9c0\uc0c1\uc8fc\ucc28\uc7a5", "lat": "37.5166513", "lng": "126.8633139", "useTime": "24\uc2dc\uac04 \uc774\uc6a9\uac00\ub2a5", "busiId": "CU", "bnm": "\uc528\uc5b4\uc2a4", "busiNm": "(\uc8fc)\uc528\uc5b4\uc2a4", "busiCall": "1522-2640", "stat": "9", "statUpdDt": "20220114150810", "lastTsdt": "20220109224624", "lastTedt": "20220109233356", "nowTsdt": "20220109224624", "powerType": null, "output": null, "method": "\ub2e8\ub3c5", "zcode": "11", "zscode": "11470", "kind": "A0", "kindDetail": "A004", "parkingFree": "N", "note": null, "limitYn": "Y", "limitDetail": "\uc2dc\uc124 \uc0c1\ud669\uc5d0 \ub530\ub77c \uc774\uc6a9\uc774 \uc81c\ud55c\ub420 \uc218 \uc788\uc74c", "delYn": "N", "delDetail": null}, {"statNm": "\uc591\ucc9c\ubb38\ud654\ud68c\uad00", "statId": "CU201001", "chgerId": "08", "chgerType": "02", "addr": "\uc11c\uc6b8\ud2b9\ubcc4\uc2dc \uc591\ucc9c\uad6c \ubaa9\ub3d9\uc11c\ub85c 367", "location": "\ub3c4\ub85c\uc606\uc9c0\uc0c1\uc8fc\ucc28\uc7a5", "lat": "37.5166513", "lng": "126.8633139", "useTime": "24\uc2dc\uac04 \uc774\uc6a9\uac00\ub2a5", "busiId": "CU", "bnm": "\uc528\uc5b4\uc2a4", "busiNm": "(\uc8fc)\uc528\uc5b4\uc2a4", "busiCall": "1522-2640", "stat": "9", "statUpdDt": "20220114151310", "lastTsdt": "20220109121732", "lastTedt": "20220109122102", "nowTsdt": "20220109121732", "powerType": null, "output": null, "method": null, "zcode": "11", "zscode": "11470", "kind": "A0", "kindDetail": "A004", "parkingFree": "N", "note": null, "limitYn": "Y", "limitDetail": "\uc2dc\uc124 \uc0c1\ud669\uc5d0 \ub530\ub77c \uc774\uc6a9\uc774 \uc81c\ud55c\ub420 \uc218 \uc788\uc74c", "delYn": "N", "delDetail": null}, {"statNm": "\uc591\ucc9c\ubb38\ud654\ud68c\uad00", "statId": "CU201001", "chgerId": "09", "chgerType": "02", "addr": "\uc11c\uc6b8\ud2b9\ubcc4\uc2dc \uc591\ucc9c\uad6c \ubaa9\ub3d9\uc11c\ub85c 367", "location": "\ub3c4\ub85c\uc606\uc9c0\uc0c1\uc8fc\ucc28\uc7a5", "lat": "37.5166513", "lng": "126.8633139", "useTime": "24\uc2dc\uac04 \uc774\uc6a9\uac00\ub2a5", "busiId": "CU", "bnm": "\uc528\uc5b4\uc2a4", "busiNm": "(\uc8fc)\uc528\uc5b4\uc2a4", "busiCall": "1522-2640", "stat": "9", "statUpdDt": "20220105200810", "lastTsdt": "20220104202842", "lastTedt": "20220104203929", "nowTsdt": "20220104202842", "powerType": null, "output": null, "method": null, "zcode": "11", "zscode": "11470", "kind": "A0", "kindDetail": "A004", "parkingFree": "N", "note": null, "limitYn": "Y", "limitDetail": "\uc2dc\uc124 \uc0c1\ud669\uc5d0 \ub530\ub77c \uc774\uc6a9\uc774 \uc81c\ud55c\ub420 \uc218 \uc788\uc74c", "delYn": "N", "delDetail": null}, {"statNm": "\uc591\ucc9c\ubb38\ud654\ud68c\uad00", "statId": "CU201001", "chgerId": "10", "chgerType": "02", "addr": "\uc11c\uc6b8\ud2b9\ubcc4\uc2dc \uc591\ucc9c\uad6c \ubaa9\ub3d9\uc11c\ub85c 367", "location": "\ub3c4\ub85c\uc606\uc9c0\uc0c1\uc8fc\ucc28\uc7a5", "lat": "37.5166513", "lng": "126.8633139", "useTime": "24\uc2dc\uac04 \uc774\uc6a9\uac00\ub2a5", "busiId": "CU", "bnm": "\uc528\uc5b4\uc2a4", "busiNm": "(\uc8fc)\uc528\uc5b4\uc2a4", "busiCall": "1522-2640", "stat": "9", "statUpdDt": "20220105201810", "lastTsdt": "20220105130557", "lastTedt": "20220105185800", "nowTsdt": "20220105130557", "powerType": null, "output": null, "method": null, "zcode": "11", "zscode": "11470", "kind": "A0", "kindDetail": "A004", "parkingFree": "N", "note": null, "limitYn": "Y", "limitDetail": "\uc2dc\uc124 \uc0c1\ud669\uc5d0 \ub530\ub77c \uc774\uc6a9\uc774 \uc81c\ud55c\ub420 \uc218 \uc788\uc74c", "delYn": "N", "delDetail": null}, {"statNm": "\uc591\ucc9c\ubb38\ud654\ud68c\uad00", "statId": "CU201001", "chgerId": "11", "chgerType": "02", "addr": "\uc11c\uc6b8\ud2b9\ubcc4\uc2dc \uc591\ucc9c\uad6c \ubaa9\ub3d9\uc11c\ub85c 367", "location": "\ub3c4\ub85c\uc606\uc9c0\uc0c1\uc8fc\ucc28\uc7a5", "lat": "37.5166513", "lng": "126.8633139", "useTime": "24\uc2dc\uac04 \uc774\uc6a9\uac00\ub2a5", "busiId": "CU", "bnm": "\uc528\uc5b4\uc2a4", "busiNm": "(\uc8fc)\uc528\uc5b4\uc2a4", "busiCall": "1522-2640", "stat": "9", "statUpdDt": "20220105201310", "lastTsdt": "20211228210336", "lastTedt": "20211228210721", "nowTsdt": "20211228210336", "powerType": null, "output": null, "method": null, "zcode": "11", "zscode": "11470", "kind": "A0", "kindDetail": "A004", "parkingFree": "N", "note": null, "limitYn": "Y", "limitDetail": "\uc2dc\uc124 \uc0c1\ud669\uc5d0 \ub530\ub77c \uc774\uc6a9\uc774 \uc81c\ud55c\ub420 \uc218 \uc788\uc74c", "delYn": "N", "delDetail": null}, {"statNm": "\uc591\ucc9c\ubb38\ud654\ud68c\uad00", "statId": "CU201001", "chgerId": "12", "chgerType": "02", "addr": "\uc11c\uc6b8\ud2b9\ubcc4\uc2dc \uc591\ucc9c\uad6c \ubaa9\ub3d9\uc11c\ub85c 367", "location": "\ub3c4\ub85c\uc606\uc9c0\uc0c1\uc8fc\ucc28\uc7a5", "lat": "37.5166513", "lng": "126.8633139", "useTime": "24\uc2dc\uac04 \uc774\uc6a9\uac00\ub2a5", "busiId": "CU", "bnm": "\uc528\uc5b4\uc2a4", "busiNm": "(\uc8fc)\uc528\uc5b4\uc2a4", "busiCall": "1522-2640", "stat": "9", "statUpdDt": "20220105201310", "lastTsdt": "20220105111949", "lastTedt": "20220105111949", "nowTsdt": "20220105111949", "powerType": null, "output": null, "method": null, "zcode": "11", "zscode": "11470", "kind": "A0", "kindDetail": "A004", "parkingFree": "N", "note": null, "limitYn": "Y", "limitDetail": "\uc2dc\uc124 \uc0c1\ud669\uc5d0 \ub530\ub77c \uc774\uc6a9\uc774 \uc81c\ud55c\ub420 \uc218 \uc788\uc74c", "delYn": "N", "delDetail": null}, {"statNm": "\uc591\ucc9c\ubb38\ud654\ud68c\uad00", "statId": "CU201001", "chgerId": "13", "chgerType": "02", "addr": "\uc11c\uc6b8\ud2b9\ubcc4\uc2dc \uc591\ucc9c\uad6c \ubaa9\ub3d9\uc11c\ub85c 367", "location": "\ub3c4\ub85c\uc606\uc9c0\uc0c1\uc8fc\ucc28\uc7a5", "lat": "37.5166513", "lng": "126.8633139", "useTime": "24\uc2dc\uac04 \uc774\uc6a9\uac00\ub2a5", "busiId": "CU", "bnm": "\uc528\uc5b4\uc2a4", "busiNm": "(\uc8fc)\uc528\uc5b4\uc2a4", "busiCall": "1522-2640", "stat": "9", "statUpdDt": "20220105200810", "lastTsdt": "20220104194010", "lastTedt": "20220104211704", "nowTsdt": "20220104194010", "powerType": null, "output": null, "method": null, "zcode": "11", "zscode": "11470", "kind": "A0", "kindDetail": "A004", "parkingFree": "N", "note": null, "limitYn": "Y", "limitDetail": "\uc2dc\uc124 \uc0c1\ud669\uc5d0 \ub530\ub77c \uc774\uc6a9\uc774 \uc81c\ud55c\ub420 \uc218 \uc788\uc74c", "delYn": "N", "delDetail": null}, {"statNm": "\uc591\ucc9c\ubb38\ud654\ud68c\uad00", "statId": "CU201001", "chgerId": "14", "chgerType": "02", "addr": "\uc11c\uc6b8\ud2b9\ubcc4\uc2dc \uc591\ucc9c\uad6c \ubaa9\ub3d9\uc11c\ub85c 367", "location": "\ub3c4\ub85c\uc606\uc9c0\uc0c1\uc8fc\ucc28\uc7a5", "lat": "37.5166513", "lng": "126.8633139", "useTime": "24\uc2dc\uac04 \uc774\uc6a9\uac00\ub2a5", "busiId": "CU", "bnm": "\uc528\uc5b4\uc2a4", "busiNm": "(\uc8fc)\uc528\uc5b4\uc2a4", "busiCall": "1522-2640", "stat": "9", "statUpdDt": "20220105200810", "lastTsdt": "20220104174956", "lastTedt": "20220104193140", "nowTsdt": "20220104174956", "powerType": null, "output": null, "method": null, "zcode": "11", "zscode": "11470", "kind": "A0", "kindDetail": "A004", "parkingFree": "N", "note": null, "limitYn": "Y", "limitDetail": "\uc2dc\uc124 \uc0c1\ud669\uc5d0 \ub530\ub77c \uc774\uc6a9\uc774 \uc81c\ud55c\ub420 \uc218 \uc788\uc74c", "delYn": "N", "delDetail": null}, {"statNm": "\uc591\ucc9c\ubb38\ud654\ud68c\uad00", "statId": "CU201001", "chgerId": "15", "chgerType": "02", "addr": "\uc11c\uc6b8\ud2b9\ubcc4\uc2dc \uc591\ucc9c\uad6c \ubaa9\ub3d9\uc11c\ub85c 367", "location": "\ub3c4\ub85c\uc606\uc9c0\uc0c1\uc8fc\ucc28\uc7a5", "lat": "37.5166513", "lng": "126.8633139", "useTime": "24\uc2dc\uac04 \uc774\uc6a9\uac00\ub2a5", "busiId": "CU", "bnm": "\uc528\uc5b4\uc2a4", "busiNm": "(\uc8fc)\uc528\uc5b4\uc2a4", "busiCall": "1522-2640", "stat": "9", "statUpdDt": "20220105200310", "lastTsdt": "20211211131320", "lastTedt": "20211211131705", "nowTsdt": "20211211131320", "powerType": null, "output": null, "method": null, "zcode": "11", "zscode": "11470", "kind": "A0", "kindDetail": "A004", "parkingFree": "N", "note": null, "limitYn": "Y", "limitDetail": "\uc2dc\uc124 \uc0c1\ud669\uc5d0 \ub530\ub77c \uc774\uc6a9\uc774 \uc81c\ud55c\ub420 \uc218 \uc788\uc74c", "delYn": "N", "delDetail": null}, {"statNm": "\uc591\ucc9c\ubb38\ud654\ud68c\uad00", "statId": "CU201001", "chgerId": "16", "chgerType": "02", "addr": "\uc11c\uc6b8\ud2b9\ubcc4\uc2dc \uc591\ucc9c\uad6c \ubaa9\ub3d9\uc11c\ub85c 367", "location": "\ub3c4\ub85c\uc606\uc9c0\uc0c1\uc8fc\ucc28\uc7a5", "lat": "37.5166513", "lng": "126.8633139", "useTime": "24\uc2dc\uac04 \uc774\uc6a9\uac00\ub2a5", "busiId": "CU", "bnm": "\uc528\uc5b4\uc2a4", "busiNm": "(\uc8fc)\uc528\uc5b4\uc2a4", "busiCall": "1522-2640", "stat": "9", "statUpdDt": "20220105200310", "lastTsdt": "20211216175452", "lastTedt": "20211216175709", "nowTsdt": "20211216175452", "powerType": null, "output": null, "method": null, "zcode": "11", "zscode": "11470", "kind": "A0", "kindDetail": "A004", "parkingFree": "N", "note": null, "limitYn": "Y", "limitDetail": "\uc2dc\uc124 \uc0c1\ud669\uc5d0 \ub530\ub77c \uc774\uc6a9\uc774 \uc81c\ud55c\ub420 \uc218 \uc788\uc74c", "delYn": "N", "delDetail": null}, {"statNm": "\uc591\ucc9c\ubb38\ud654\ud68c\uad00", "statId": "CU201001", "chgerId": "17", "chgerType": "02", "addr": "\uc11c\uc6b8\ud2b9\ubcc4\uc2dc \uc591\ucc9c\uad6c \ubaa9\ub3d9\uc11c\ub85c 367", "location": "\ub3c4\ub85c\uc606\uc9c0\uc0c1\uc8fc\ucc28\uc7a5", "lat": "37.5166513", "lng": "126.8633139", "useTime": "24\uc2dc\uac04 \uc774\uc6a9\uac00\ub2a5", "busiId": "CU", "bnm": "\uc528\uc5b4\uc2a4", "busiNm": "(\uc8fc)\uc528\uc5b4\uc2a4", "busiCall": "1522-2640", "stat": "9", "statUpdDt": "20220107000310", "lastTsdt": "20220106075322", "lastTedt": "20220106010653", "nowTsdt": "20220106075322", "powerType": null, "output": null, "method": null, "zcode": "11", "zscode": "11470", "kind": "A0", "kindDetail": "A004", "parkingFree": "N", "note": null, "limitYn": "Y", "limitDetail": "\uc2dc\uc124 \uc0c1\ud669\uc5d0 \ub530\ub77c \uc774\uc6a9\uc774 \uc81c\ud55c\ub420 \uc218 \uc788\uc74c", "delYn": "N", "delDetail": null}, {"statNm": "\uc591\ucc9c\ubb38\ud654\ud68c\uad00", "statId": "CU201001", "chgerId": "18", "chgerType": "02", "addr": "\uc11c\uc6b8\ud2b9\ubcc4\uc2dc \uc591\ucc9c\uad6c \ubaa9\ub3d9\uc11c\ub85c 367", "location": "\ub3c4\ub85c\uc606\uc9c0\uc0c1\uc8fc\ucc28\uc7a5", "lat": "37.5166513", "lng": "126.8633139", "useTime": "24\uc2dc\uac04 \uc774\uc6a9\uac00\ub2a5", "busiId": "CU", "bnm": "\uc528\uc5b4\uc2a4", "busiNm": "(\uc8fc)\uc528\uc5b4\uc2a4", "busiCall": "1522-2640", "stat": "9", "statUpdDt": "20220107000310", "lastTsdt": "20220105203623", "lastTedt": "20220105234601", "nowTsdt": "20220105203623", "powerType": null, "output": null, "method": null, "zcode": "11", "zscode": "11470", "kind": "A0", "kindDetail": "A004", "parkingFree": "N", "note": null, "limitYn": "Y", "limitDetail": "\uc2dc\uc124 \uc0c1\ud669\uc5d0 \ub530\ub77c \uc774\uc6a9\uc774 \uc81c\ud55c\ub420 \uc218 \uc788\uc74c", "delYn": "N", "delDetail": null}, {"statNm": "\uc591\ucc9c\ubb38\ud654\ud68c\uad00", "statId": "CU201001", "chgerId": "19", "chgerType": "02", "addr": "\uc11c\uc6b8\ud2b9\ubcc4\uc2dc \uc591\ucc9c\uad6c \ubaa9\ub3d9\uc11c\ub85c 367", "location": "\ub3c4\ub85c\uc606\uc9c0\uc0c1\uc8fc\ucc28\uc7a5", "lat": "37.5166513", "lng": "126.8633139", "useTime": "24\uc2dc\uac04 \uc774\uc6a9\uac00\ub2a5", "busiId": "CU", "bnm": "\uc528\uc5b4\uc2a4", "busiNm": "(\uc8fc)\uc528\uc5b4\uc2a4", "busiCall": "1522-2640", "stat": "9", "statUpdDt": "20220105200310", "lastTsdt": "20220105182956", "lastTedt": "20220105182956", "nowTsdt": "20220105182956", "powerType": null, "output": null, "method": null, "zcode": "11", "zscode": "11470", "kind": "A0", "kindDetail": "A004", "parkingFree": "N", "note": null, "limitYn": "Y", "limitDetail": "\uc2dc\uc124 \uc0c1\ud669\uc5d0 \ub530\ub77c \uc774\uc6a9\uc774 \uc81c\ud55c\ub420 \uc218 \uc788\uc74c", "delYn": "N", "delDetail": null}, {"statNm": "\uc591\ucc9c\ubb38\ud654\ud68c\uad00", "statId": "CU201001", "chgerId": "20", "chgerType": "02", "addr": "\uc11c\uc6b8\ud2b9\ubcc4\uc2dc \uc591\ucc9c\uad6c \ubaa9\ub3d9\uc11c\ub85c 367", "location": "\ub3c4\ub85c\uc606\uc9c0\uc0c1\uc8fc\ucc28\uc7a5", "lat": "37.5166513", "lng": "126.8633139", "useTime": "24\uc2dc\uac04 \uc774\uc6a9\uac00\ub2a5", "busiId": "CU", "bnm": "\uc528\uc5b4\uc2a4", "busiNm": "(\uc8fc)\uc528\uc5b4\uc2a4", "busiCall": "1522-2640", "stat": "9", "statUpdDt": "20220105200310", "lastTsdt": "20211216174852", "lastTedt": "20211216175222", "nowTsdt": "20211216174852", "powerType": null, "output": null, "method": null, "zcode": "11", "zscode": "11470", "kind": "A0", "kindDetail": "A004", "parkingFree": "N", "note": null, "limitYn": "Y", "limitDetail": "\uc2dc\uc124 \uc0c1\ud669\uc5d0 \ub530\ub77c \uc774\uc6a9\uc774 \uc81c\ud55c\ub420 \uc218 \uc788\uc74c", "delYn": "N", "delDetail": null}]