[{"statNm": "\uc11c\uc6b8\uc2dc \ud559\uc5ec\uc6b8\uc5ed\uacf5\uc601\uc8fc\ucc28\uc7a5(\uae09\uc18d)", "statId": "EV003443", "chgerId": "02", "chgerType": "04", "addr": "\uc11c\uc6b8\ud2b9\ubcc4\uc2dc \uac15\ub0a8\uad6c \ub0a8\ubd80\uc21c\ud658\ub85c \uc9c0\ud558 3104", "location": "null", "lat": "37.496717186", "lng": "127.07171897", "useTime": "24\uc2dc\uac04 \uc774\uc6a9\uac00\ub2a5", "busiId": "EV", "bnm": "\uc5d0\ubc84\uc628", "busiNm": "\uc8fc\uc2dd\ud68c\uc0ac \uc5d0\ubc84\uc628", "busiCall": "1661-7766", "stat": "2", "statUpdDt": "20220708163111", "lastTsdt": "20220708154126", "lastTedt": "20220708162737", "nowTsdt": "20220708154126", "powerType": null, "output": "100", "method": "\ub3d9\uc2dc", "zcode": "11", "zscode": "11680", "kind": "B0", "kindDetail": "B001", "parkingFree": "N", "note": "24\uc2dc\uac04 \uc774\uc6a9\uac00\ub2a5", "limitYn": "N", "limitDetail": "\uc678\ubd80\uc778 \uc0ac\uc6a9\ubd88\uac00", "delYn": "N", "delDetail": null}]