[{"statNm": "\uacbd\uae30\uace0\uc591_DMC\ud638\ubc18\ubca0\ub974\ub514\uc6c0\ub354\ud3ec\ub8084\ub2e8\uc9c0406\ub3d9", "statId": "EV003244", "chgerId": "02", "chgerType": "02", "addr": "\uacbd\uae30\ub3c4 \uace0\uc591\uc2dc \ub355\uc591\uad6c \ud5a5\uae30\ub85c 77", "location": "null", "lat": "37.596977590575", "lng": "126.8915253705", "useTime": "24\uc2dc\uac04 \uc774\uc6a9\uac00\ub2a5,\uc785\uc8fc\ubbfc\ub9cc \uc0ac\uc6a9\uac00\ub2a5 \uac70\uc8fc\uc790\uc678\ucd9c\uc785\uc81c\ud55c", "busiId": "EV", "bnm": "\uc5d0\ubc84\uc628", "busiNm": "\uc8fc\uc2dd\ud68c\uc0ac \uc5d0\ubc84\uc628", "busiCall": "1661-7766", "stat": "3", "statUpdDt": "20220708122353", "lastTsdt": "20220707194514", "lastTedt": "20220708014525", "nowTsdt": "20220708122201", "powerType": null, "output": "7", "method": "\ub2e8\ub3c5", "zcode": "41", "zscode": "41280", "kind": "H0", "kindDetail": "H001", "parkingFree": "Y", "note": "\uc785\uc8fc\ubbfc\ub9cc \uc0ac\uc6a9\uac00\ub2a5 \uac70\uc8fc\uc790 \uc678 \ucd9c\uc785\uc81c\ud55c", "limitYn": "N", "limitDetail": "\uc678\ubd80\uc778 \uc0ac\uc6a9\ubd88\uac00", "delYn": "N", "delDetail": null}, {"statNm": "\uacbd\uae30\uace0\uc591_DMC\ud638\ubc18\ubca0\ub974\ub514\uc6c0\ub354\ud3ec\ub8084\ub2e8\uc9c0406\ub3d9", "statId": "EV003244", "chgerId": "03", "chgerType": "02", "addr": "\uacbd\uae30\ub3c4 \uace0\uc591\uc2dc \ub355\uc591\uad6c \ud5a5\uae30\ub85c 77", "location": "null", "lat": "37.596977590575", "lng": "126.8915253705", "useTime": "24\uc2dc\uac04 \uc774\uc6a9\uac00\ub2a5,\uc785\uc8fc\ubbfc\ub9cc \uc0ac\uc6a9\uac00\ub2a5 \uac70\uc8fc\uc790\uc678\ucd9c\uc785\uc81c\ud55c", "busiId": "EV", "bnm": "\uc5d0\ubc84\uc628", "busiNm": "\uc8fc\uc2dd\ud68c\uc0ac \uc5d0\ubc84\uc628", "busiCall": "1661-7766", "stat": "2", "statUpdDt": "20220708075112", "lastTsdt": "20220707213232", "lastTedt": "20220708073215", "nowTsdt": "20220707213232", "powerType": null, "output": "7", "method": "\ub2e8\ub3c5", "zcode": "41", "zscode": "41280", "kind": "H0", "kindDetail": "H001", "parkingFree": "Y", "note": "\uc785\uc8fc\ubbfc\ub9cc \uc0ac\uc6a9\uac00\ub2a5 \uac70\uc8fc\uc790 \uc678 \ucd9c\uc785\uc81c\ud55c", "limitYn": "N", "limitDetail": "\uc678\ubd80\uc778 \uc0ac\uc6a9\ubd88\uac00", "delYn": "N", "delDetail": null}, {"statNm": "\uacbd\uae30\uace0\uc591_DMC\ud638\ubc18\ubca0\ub974\ub514\uc6c0\ub354\ud3ec\ub8084\ub2e8\uc9c0406\ub3d9", "statId": "EV003244", "chgerId": "04", "chgerType": "02", "addr": "\uacbd\uae30\ub3c4 \uace0\uc591\uc2dc \ub355\uc591\uad6c \ud5a5\uae30\ub85c 77", "location": "null", "lat": "37.596977590575", "lng": "126.8915253705", "useTime": "24\uc2dc\uac04 \uc774\uc6a9\uac00\ub2a5,\uc785\uc8fc\ubbfc\ub9cc \uc0ac\uc6a9\uac00\ub2a5 \uac70\uc8fc\uc790\uc678\ucd9c\uc785\uc81c\ud55c", "busiId": "EV", "bnm": "\uc5d0\ubc84\uc628", "busiNm": "\uc8fc\uc2dd\ud68c\uc0ac \uc5d0\ubc84\uc628", "busiCall": "1661-7766", "stat": "2", "statUpdDt": "20220708144404", "lastTsdt": "20220708074021", "lastTedt": "20220708082810", "nowTsdt": "20220708074021", "powerType": null, "output": "7", "method": "\ub2e8\ub3c5", "zcode": "41", "zscode": "41280", "kind": "H0", "kindDetail": "H001", "parkingFree": "Y", "note": "\uc785\uc8fc\ubbfc\ub9cc \uc0ac\uc6a9\uac00\ub2a5 \uac70\uc8fc\uc790 \uc678 \ucd9c\uc785\uc81c\ud55c", "limitYn": "N", "limitDetail": "\uc678\ubd80\uc778 \uc0ac\uc6a9\ubd88\uac00", "delYn": "N", "delDetail": null}, {"statNm": "\uacbd\uae30\uace0\uc591_DMC\ud638\ubc18\ubca0\ub974\ub514\uc6c0\ub354\ud3ec\ub8084\ub2e8\uc9c0406\ub3d9", "statId": "EV003244", "chgerId": "05", "chgerType": "02", "addr": "\uacbd\uae30\ub3c4 \uace0\uc591\uc2dc \ub355\uc591\uad6c \ud5a5\uae30\ub85c 77", "location": "null", "lat": "37.596977590575", "lng": "126.8915253705", "useTime": "24\uc2dc\uac04 \uc774\uc6a9\uac00\ub2a5,\uc785\uc8fc\ubbfc\ub9cc \uc0ac\uc6a9\uac00\ub2a5 \uac70\uc8fc\uc790\uc678\ucd9c\uc785\uc81c\ud55c", "busiId": "EV", "bnm": "\uc5d0\ubc84\uc628", "busiNm": "\uc8fc\uc2dd\ud68c\uc0ac \uc5d0\ubc84\uc628", "busiCall": "1661-7766", "stat": "2", "statUpdDt": "20220707184214", "lastTsdt": "20220707171839", "lastTedt": "20220707182136", "nowTsdt": "20220707171839", "powerType": null, "output": "7", "method": "\ub2e8\ub3c5", "zcode": "41", "zscode": "41280", "kind": "H0", "kindDetail": "H001", "parkingFree": "Y", "note": "\uc785\uc8fc\ubbfc\ub9cc \uc0ac\uc6a9\uac00\ub2a5 \uac70\uc8fc\uc790 \uc678 \ucd9c\uc785\uc81c\ud55c", "limitYn": "N", "limitDetail": "\uc678\ubd80\uc778 \uc0ac\uc6a9\ubd88\uac00", "delYn": "N", "delDetail": null}]