[{"statNm": "\uc548\uc5911\ubc88\uac00 \ub178\uc678\uc8fc\ucc28\uc7a5", "statId": "GN055033", "chgerId": "02", "chgerType": "04", "addr": "\uacbd\uae30\ub3c4 \uc548\uc591\uc2dc \ub9cc\uc548\uad6c \ub9cc\uc548\ub85c 204", "location": "\uc785\uad6c \ub9de\uc740\ud3b8 \ucee8\ud14c\uc774\ub108 \uc606", "lat": "37.399169516", "lng": "126.92446835", "useTime": "24\uc2dc\uac04 \uc774\uc6a9\uac00\ub2a5", "busiId": "GN", "bnm": "\uc9c0\ucee4\ub125\ud2b8", "busiNm": "\uc548\uc5911\ubc88\uac00 \ub178\uc678\uc8fc\ucc28\uc7a5", "busiCall": "\uc548\uc5911\ubc88\uac00 \ub178\uc678\uc8fc\ucc28\uc7a5", "stat": "2", "statUpdDt": "20220708170054", "lastTsdt": "20220708164045", "lastTedt": "20220708165816", "nowTsdt": "20220708164045", "powerType": null, "output": "50", "method": "\ub3d9\uc2dc", "zcode": "41", "zscode": "41170", "kind": "A0", "kindDetail": "A004", "parkingFree": "N", "note": null, "limitYn": "N", "limitDetail": "\uc2dc\uc124 \uc0c1\ud669\uc5d0 \ub530\ub77c \uc774\uc6a9\uc774 \uc81c\ud55c\ub420 \uc218 \uc788\uc74c, \uac70\uc8fc\uc790\uc678 \ucd9c\uc785\uc81c\ud55c", "delYn": "N", "delDetail": null}]