[{"statNm": "\uc6d0\ub2f9\ud48d\ub9bc\uc544\uc774\uc6d0\uc544\ud30c\ud2b8", "statId": "HE192274", "chgerId": "02", "chgerType": "02", "addr": "\uc778\ucc9c\uad11\uc5ed\uc2dc \uc11c\uad6c \uc6d0\ub2f9\ub300\ub85c840\ubc88\uae38 21", "location": "null", "lat": "37.591466", "lng": "126.696556", "useTime": "24\uc2dc\uac04 \uc774\uc6a9\uac00\ub2a5", "busiId": "HE", "bnm": "\ud55c\uad6d\uc804\uae30\ucc28\ucda9\uc804\uc11c\ube44\uc2a4", "busiNm": "\ud55c\uad6d\uc804\uae30\ucc28\ucda9\uc804\uc11c\ube44\uc2a4", "busiCall": "1522-1782", "stat": "3", "statUpdDt": "20220708032124", "lastTsdt": "20220707044902", "lastTedt": "20220707130914", "nowTsdt": null, "powerType": null, "output": null, "method": null, "zcode": "28", "zscode": "28260", "kind": "H0", "kindDetail": "H001", "parkingFree": "Y", "note": null, "limitYn": "Y", "limitDetail": "\uac70\uc8fc\uc790\uc678 \ucd9c\uc785\uc81c\ud55c", "delYn": "N", "delDetail": null}, {"statNm": "\uc6d0\ub2f9\ud48d\ub9bc\uc544\uc774\uc6d0\uc544\ud30c\ud2b8", "statId": "HE192274", "chgerId": "03", "chgerType": "02", "addr": "\uc778\ucc9c\uad11\uc5ed\uc2dc \uc11c\uad6c \uc6d0\ub2f9\ub300\ub85c840\ubc88\uae38 21", "location": "null", "lat": "37.591466", "lng": "126.696556", "useTime": "24\uc2dc\uac04 \uc774\uc6a9\uac00\ub2a5", "busiId": "HE", "bnm": "\ud55c\uad6d\uc804\uae30\ucc28\ucda9\uc804\uc11c\ube44\uc2a4", "busiNm": "\ud55c\uad6d\uc804\uae30\ucc28\ucda9\uc804\uc11c\ube44\uc2a4", "busiCall": "1522-1782", "stat": "2", "statUpdDt": "20220708063724", "lastTsdt": "20220707165237", "lastTedt": "20220708003936", "nowTsdt": null, "powerType": null, "output": null, "method": null, "zcode": "28", "zscode": "28260", "kind": "H0", "kindDetail": "H001", "parkingFree": "Y", "note": null, "limitYn": "Y", "limitDetail": "\uac70\uc8fc\uc790\uc678 \ucd9c\uc785\uc81c\ud55c", "delYn": "N", "delDetail": null}, {"statNm": "\uc6d0\ub2f9\ud48d\ub9bc\uc544\uc774\uc6d0\uc544\ud30c\ud2b8", "statId": "HE192274", "chgerId": "04", "chgerType": "02", "addr": "\uc778\ucc9c\uad11\uc5ed\uc2dc \uc11c\uad6c \uc6d0\ub2f9\ub300\ub85c840\ubc88\uae38 21", "location": "null", "lat": "37.591466", "lng": "126.696556", "useTime": "24\uc2dc\uac04 \uc774\uc6a9\uac00\ub2a5", "busiId": "HE", "bnm": "\ud55c\uad6d\uc804\uae30\ucc28\ucda9\uc804\uc11c\ube44\uc2a4", "busiNm": "\ud55c\uad6d\uc804\uae30\ucc28\ucda9\uc804\uc11c\ube44\uc2a4", "busiCall": "1522-1782", "stat": "2", "statUpdDt": "20220707030225", "lastTsdt": "20220706114615", "lastTedt": "20220706152549", "nowTsdt": null, "powerType": null, "output": null, "method": null, "zcode": "28", "zscode": "28260", "kind": "H0", "kindDetail": "H001", "parkingFree": "Y", "note": null, "limitYn": "Y", "limitDetail": "\uac70\uc8fc\uc790\uc678 \ucd9c\uc785\uc81c\ud55c", "delYn": "N", "delDetail": null}]