[{"statNm": "\uc778\uc131\uc2e4\uc5c5", "statId": "KL002244", "chgerId": "02", "chgerType": "02", "addr": "\uc778\ucc9c\uad11\uc5ed\uc2dc \uc11c\uad6c \uccad\ub77c\ud55c\ub0b4\ub85c100\ubc88\uae38 24", "location": "null", "lat": "37.53383", "lng": "126.63022", "useTime": "24\uc2dc\uac04 \uc774\uc6a9\uac00\ub2a5", "busiId": "KL", "bnm": "\ud074\ub9b0\uc77c\ub809\uc2a4", "busiNm": "(\uc8fc)\ud074\ub9b0\uc77c\ub809\uc2a4", "busiCall": "1811-1350", "stat": "2", "statUpdDt": "20220701111507", "lastTsdt": "20220630122151", "lastTedt": "20220630152606", "nowTsdt": "20220630122151", "powerType": null, "output": "7", "method": "\ub2e8\ub3c5", "zcode": "28", "zscode": "28260", "kind": "A0", "kindDetail": "A003", "parkingFree": "Y", "note": null, "limitYn": "N", "limitDetail": null, "delYn": "N", "delDetail": null}, {"statNm": "\uc778\uc131\uc2e4\uc5c5", "statId": "KL002244", "chgerId": "03", "chgerType": "02", "addr": "\uc778\ucc9c\uad11\uc5ed\uc2dc \uc11c\uad6c \uccad\ub77c\ud55c\ub0b4\ub85c100\ubc88\uae38 24", "location": "null", "lat": "37.53383", "lng": "126.63022", "useTime": "24\uc2dc\uac04 \uc774\uc6a9\uac00\ub2a5", "busiId": "KL", "bnm": "\ud074\ub9b0\uc77c\ub809\uc2a4", "busiNm": "(\uc8fc)\ud074\ub9b0\uc77c\ub809\uc2a4", "busiCall": "1811-1350", "stat": "2", "statUpdDt": "20220708113402", "lastTsdt": "20220708095320", "lastTedt": "20220708112840", "nowTsdt": "20220708095320", "powerType": null, "output": "7", "method": "\ub2e8\ub3c5", "zcode": "28", "zscode": "28260", "kind": "A0", "kindDetail": "A003", "parkingFree": "Y", "note": null, "limitYn": "N", "limitDetail": null, "delYn": "N", "delDetail": null}, {"statNm": "\uc778\uc131\uc2e4\uc5c5", "statId": "KL002244", "chgerId": "04", "chgerType": "04", "addr": "\uc778\ucc9c\uad11\uc5ed\uc2dc \uc11c\uad6c \uccad\ub77c\ud55c\ub0b4\ub85c100\ubc88\uae38 24", "location": "null", "lat": "37.53383", "lng": "126.63022", "useTime": "24\uc2dc\uac04 \uc774\uc6a9\uac00\ub2a5", "busiId": "KL", "bnm": "\ud074\ub9b0\uc77c\ub809\uc2a4", "busiNm": "(\uc8fc)\ud074\ub9b0\uc77c\ub809\uc2a4", "busiCall": "1811-1350", "stat": "2", "statUpdDt": "20220702085001", "lastTsdt": "20210726142706", "lastTedt": "20210726142833", "nowTsdt": null, "powerType": null, "output": "50", "method": "\ub2e8\ub3c5", "zcode": "28", "zscode": "28260", "kind": "A0", "kindDetail": "A003", "parkingFree": "Y", "note": null, "limitYn": "N", "limitDetail": null, "delYn": "N", "delDetail": null}]