[{"statNm": "\ube5b\uac00\ub78c\ub85c\uc81c\ube44\uc559", "statId": "KP002315", "chgerId": "02", "chgerType": "02", "addr": "\uc804\ub77c\ub0a8\ub3c4 \ub098\uc8fc\uc2dc \ube5b\uac00\ub78c\ub3d9 \uadf8\ub9b0\ub85c 153", "location": "null", "lat": "35.0108205021", "lng": "126.7831812192", "useTime": null, "busiId": "KP", "bnm": "\ud55c\uad6d\uc804\ub825\uacf5\uc0ac", "busiNm": "\ud55c\uad6d\uc804\ub825", "busiCall": "null", "stat": "2", "statUpdDt": "20220708004201", "lastTsdt": "20220707185838", "lastTedt": "20220708004128", "nowTsdt": "20220707185838", "powerType": null, "output": null, "method": null, "zcode": "46", "zscode": null, "kind": "70", "kindDetail": "7011", "parkingFree": "Y", "note": null, "limitYn": "Y", "limitDetail": "\uc2dc\uc124 \uc0c1\ud669\uc5d0 \ub530\ub77c \uc774\uc6a9\uc774 \uc81c\ud55c\ub420 \uc218 \uc788\uc74c", "delYn": "N", "delDetail": null}, {"statNm": "\ube5b\uac00\ub78c\ub85c\uc81c\ube44\uc559", "statId": "KP002315", "chgerId": "03", "chgerType": "02", "addr": "\uc804\ub77c\ub0a8\ub3c4 \ub098\uc8fc\uc2dc \ube5b\uac00\ub78c\ub3d9 \uadf8\ub9b0\ub85c 153", "location": "null", "lat": "35.0108205021", "lng": "126.7831812192", "useTime": null, "busiId": "KP", "bnm": "\ud55c\uad6d\uc804\ub825\uacf5\uc0ac", "busiNm": "\ud55c\uad6d\uc804\ub825", "busiCall": "null", "stat": "2", "statUpdDt": "20220707234300", "lastTsdt": "20220707185112", "lastTedt": "20220707234208", "nowTsdt": "20220707185112", "powerType": null, "output": null, "method": null, "zcode": "46", "zscode": null, "kind": "70", "kindDetail": "7011", "parkingFree": "Y", "note": null, "limitYn": "Y", "limitDetail": "\uc2dc\uc124 \uc0c1\ud669\uc5d0 \ub530\ub77c \uc774\uc6a9\uc774 \uc81c\ud55c\ub420 \uc218 \uc788\uc74c", "delYn": "N", "delDetail": null}, {"statNm": "\ube5b\uac00\ub78c\ub85c\uc81c\ube44\uc559", "statId": "KP002315", "chgerId": "04", "chgerType": "02", "addr": "\uc804\ub77c\ub0a8\ub3c4 \ub098\uc8fc\uc2dc \ube5b\uac00\ub78c\ub3d9 \uadf8\ub9b0\ub85c 153", "location": "null", "lat": "35.0108205021", "lng": "126.7831812192", "useTime": null, "busiId": "KP", "bnm": "\ud55c\uad6d\uc804\ub825\uacf5\uc0ac", "busiNm": "\ud55c\uad6d\uc804\ub825", "busiCall": "null", "stat": "3", "statUpdDt": "20220708171801", "lastTsdt": "20220708013430", "lastTedt": "20220708062625", "nowTsdt": "20220708171747", "powerType": null, "output": null, "method": null, "zcode": "46", "zscode": null, "kind": "70", "kindDetail": "7011", "parkingFree": "Y", "note": null, "limitYn": "Y", "limitDetail": "\uc2dc\uc124 \uc0c1\ud669\uc5d0 \ub530\ub77c \uc774\uc6a9\uc774 \uc81c\ud55c\ub420 \uc218 \uc788\uc74c", "delYn": "N", "delDetail": null}, {"statNm": "\ube5b\uac00\ub78c\ub85c\uc81c\ube44\uc559", "statId": "KP002315", "chgerId": "05", "chgerType": "02", "addr": "\uc804\ub77c\ub0a8\ub3c4 \ub098\uc8fc\uc2dc \ube5b\uac00\ub78c\ub3d9 \uadf8\ub9b0\ub85c 153", "location": "null", "lat": "35.0108205021", "lng": "126.7831812192", "useTime": null, "busiId": "KP", "bnm": "\ud55c\uad6d\uc804\ub825\uacf5\uc0ac", "busiNm": "\ud55c\uad6d\uc804\ub825", "busiCall": "null", "stat": "9", "statUpdDt": "20220708164310", "lastTsdt": null, "lastTedt": null, "nowTsdt": null, "powerType": null, "output": null, "method": null, "zcode": "46", "zscode": null, "kind": "70", "kindDetail": "7011", "parkingFree": "Y", "note": null, "limitYn": "Y", "limitDetail": "\uc2dc\uc124 \uc0c1\ud669\uc5d0 \ub530\ub77c \uc774\uc6a9\uc774 \uc81c\ud55c\ub420 \uc218 \uc788\uc74c", "delYn": "N", "delDetail": null}]