[{"statNm": "\ub3d9\uc6d0\uc6b0\uc131 \ube4c\ub77c\ud2b8", "statId": "KP001147", "chgerId": "02", "chgerType": "02", "addr": "\uacbd\uc0c1\ub0a8\ub3c4 \uac70\uc81c\uc2dc \uc625\ud3ec\ub3d9 \uc625\ud3ec\ub300\ucca9\ub85c 88", "location": "null", "lat": "34.8943337063", "lng": "128.6975818115", "useTime": "24\uc2dc\uac04", "busiId": "KP", "bnm": "\ud55c\uad6d\uc804\ub825\uacf5\uc0ac", "busiNm": "\ud55c\uad6d\uc804\ub825", "busiCall": "null", "stat": "2", "statUpdDt": "20220619203101", "lastTsdt": "20220619151133", "lastTedt": "20220619202501", "nowTsdt": "20220619151133", "powerType": null, "output": null, "method": null, "zcode": "48", "zscode": null, "kind": "70", "kindDetail": "7011", "parkingFree": "Y", "note": null, "limitYn": "Y", "limitDetail": "\uc2dc\uc124 \uc0c1\ud669\uc5d0 \ub530\ub77c \uc774\uc6a9\uc774 \uc81c\ud55c\ub420 \uc218 \uc788\uc74c", "delYn": "N", "delDetail": null}]