[{"statNm": "\ub300\ub9bc\uc544\ud30c\ud2b8", "statId": "LH403200", "chgerId": "02", "chgerType": "02", "addr": "\ucda9\uccad\ub0a8\ub3c4 \uc11c\uc0b0\uc2dc \ud5a5\uad501\ub85c 12", "location": "\uad00\ub9ac\uc0ac\ubb34\uc18c \ub9de\uc740\ud3b8 \uc9c0\uc0c1\uc8fc\ucc28\uc7a5", "lat": "36.7893117", "lng": "126.456615", "useTime": "24\uc2dc\uac04 \uc774\uc6a9\uac00\ub2a5", "busiId": "LH", "bnm": "LG\ud5ec\ub85c\ube44\uc804", "busiNm": "LG\ud5ec\ub85c\ube44\uc804", "busiCall": "1855-1078", "stat": "2", "statUpdDt": "20220701101049", "lastTsdt": "20220628105020", "lastTedt": "20220628105145", "nowTsdt": "20220605190611", "powerType": null, "output": "7", "method": "\ub2e8\ub3c5", "zcode": "44", "zscode": "44210", "kind": "H0", "kindDetail": "H001", "parkingFree": "N", "note": "\uc785\uc8fc\ubbfc \uc804\uc6a9", "limitYn": "Y", "limitDetail": "\uac70\uc8fc\uc790\uc678 \ucd9c\uc785\uc774 \uc81c\ud55c\ub420 \uc218 \uc788\uc2b5\ub2c8\ub2e4.", "delYn": "N", "delDetail": null, "updateTime": "2022/07/11 19:42:28"}, {"statNm": "\ub300\ub9bc\uc544\ud30c\ud2b8", "statId": "LH403200", "chgerId": "03", "chgerType": "02", "addr": "\ucda9\uccad\ub0a8\ub3c4 \uc11c\uc0b0\uc2dc \ud5a5\uad501\ub85c 12", "location": "\uad00\ub9ac\uc0ac\ubb34\uc18c \ub9de\uc740\ud3b8 \uc9c0\uc0c1\uc8fc\ucc28\uc7a5", "lat": "36.7893117", "lng": "126.456615", "useTime": "24\uc2dc\uac04 \uc774\uc6a9\uac00\ub2a5", "busiId": "LH", "bnm": "LG\ud5ec\ub85c\ube44\uc804", "busiNm": "LG\ud5ec\ub85c\ube44\uc804", "busiCall": "1855-1078", "stat": "2", "statUpdDt": "20220701101049", "lastTsdt": "20220628105205", "lastTedt": "20220628105340", "nowTsdt": "20220605121955", "powerType": null, "output": "7", "method": "\ub2e8\ub3c5", "zcode": "44", "zscode": "44210", "kind": "H0", "kindDetail": "H001", "parkingFree": "N", "note": "\uc785\uc8fc\ubbfc \uc804\uc6a9", "limitYn": "Y", "limitDetail": "\uac70\uc8fc\uc790\uc678 \ucd9c\uc785\uc774 \uc81c\ud55c\ub420 \uc218 \uc788\uc2b5\ub2c8\ub2e4.", "delYn": "N", "delDetail": null, "updateTime": "2022/07/11 19:42:28"}]