[{"statNm": "\uc138\uc885\uc2dc \ub124\uc774\ubc84\ud0c0\uc6cc", "statId": "NESEJNAV", "chgerId": "14", "chgerType": "02", "addr": "\uc138\uc885\ud2b9\ubcc4\uc790\uce58\uc2dc \ud638\ub824\uc6b8\ub85c 9", "location": "null", "lat": "36.4770903", "lng": "127.288242", "useTime": "24\uc2dc\uac04 \uc774\uc6a9\uac00\ub2a5", "busiId": "NE", "bnm": "\uc5d0\ub108\ub137", "busiNm": "\uc8fc\uc2dd\ud68c\uc0ac \uc5d0\ub108\ub137", "busiCall": "042-863-6698", "stat": "2", "statUpdDt": "20220711100507", "lastTsdt": null, "lastTedt": null, "nowTsdt": null, "powerType": null, "output": "7", "method": "\ub2e8\ub3c5", "zcode": "36", "zscode": "36110", "kind": "E0", "kindDetail": "E006", "parkingFree": "N", "note": null, "limitYn": "N", "limitDetail": null, "delYn": "N", "delDetail": null, "updateTime": "2022/07/11 10:22:24"}, {"statNm": "\uc138\uc885\uc2dc \ub124\uc774\ubc84\ud0c0\uc6cc", "statId": "NESEJNAV", "chgerId": "15", "chgerType": "02", "addr": "\uc138\uc885\ud2b9\ubcc4\uc790\uce58\uc2dc \ud638\ub824\uc6b8\ub85c 9", "location": "null", "lat": "36.4770903", "lng": "127.288242", "useTime": "24\uc2dc\uac04 \uc774\uc6a9\uac00\ub2a5", "busiId": "NE", "bnm": "\uc5d0\ub108\ub137", "busiNm": "\uc8fc\uc2dd\ud68c\uc0ac \uc5d0\ub108\ub137", "busiCall": "042-863-6698", "stat": "2", "statUpdDt": "20220711100507", "lastTsdt": null, "lastTedt": null, "nowTsdt": null, "powerType": null, "output": "7", "method": "\ub2e8\ub3c5", "zcode": "36", "zscode": "36110", "kind": "E0", "kindDetail": "E006", "parkingFree": "N", "note": null, "limitYn": "N", "limitDetail": null, "delYn": "N", "delDetail": null, "updateTime": "2022/07/11 10:22:24"}, {"statNm": "\uc138\uc885\uc2dc \ub124\uc774\ubc84\ud0c0\uc6cc", "statId": "NESEJNAV", "chgerId": "16", "chgerType": "02", "addr": "\uc138\uc885\ud2b9\ubcc4\uc790\uce58\uc2dc \ud638\ub824\uc6b8\ub85c 9", "location": "null", "lat": "36.4770903", "lng": "127.288242", "useTime": "24\uc2dc\uac04 \uc774\uc6a9\uac00\ub2a5", "busiId": "NE", "bnm": "\uc5d0\ub108\ub137", "busiNm": "\uc8fc\uc2dd\ud68c\uc0ac \uc5d0\ub108\ub137", "busiCall": "042-863-6698", "stat": "2", "statUpdDt": "20220711100507", "lastTsdt": null, "lastTedt": null, "nowTsdt": null, "powerType": null, "output": "7", "method": "\ub2e8\ub3c5", "zcode": "36", "zscode": "36110", "kind": "E0", "kindDetail": "E006", "parkingFree": "N", "note": null, "limitYn": "N", "limitDetail": null, "delYn": "N", "delDetail": null, "updateTime": "2022/07/11 10:22:24"}]