[{"statNm": "\uc11c\uc6b8\uc2dc \ub3d9\ub300\ubb38\uad6c \uc804\ub18dSK\uc544\ud30c\ud2b8", "statId": "PI200382", "chgerId": "02", "chgerType": "02", "addr": "\uc11c\uc6b8\ud2b9\ubcc4\uc2dc \ub3d9\ub300\ubb38\uad6c \uc0ac\uac00\uc815\ub85c 148", "location": "null", "lat": "37.576659035885", "lng": "127.0615676888", "useTime": "24\uc2dc\uac04 \uc774\uc6a9\uac00\ub2a5", "busiId": "PI", "bnm": "\ucc28\uc9c0\ube44", "busiNm": "\ucc28\uc9c0\ube44", "busiCall": "1600-4047", "stat": "2", "statUpdDt": "20220708180136", "lastTsdt": "20220706222519", "lastTedt": "20220707090624", "nowTsdt": "20220706222519", "powerType": null, "output": null, "method": null, "zcode": "11", "zscode": "11230", "kind": "H0", "kindDetail": "H001", "parkingFree": "Y", "note": null, "limitYn": "Y", "limitDetail": "\uac70\uc8fc\uc790\uc678 \ucd9c\uc785\uc81c\ud55c", "delYn": "N", "delDetail": null}, {"statNm": "\uc11c\uc6b8\uc2dc \ub3d9\ub300\ubb38\uad6c \uc804\ub18dSK\uc544\ud30c\ud2b8", "statId": "PI200382", "chgerId": "03", "chgerType": "02", "addr": "\uc11c\uc6b8\ud2b9\ubcc4\uc2dc \ub3d9\ub300\ubb38\uad6c \uc0ac\uac00\uc815\ub85c 148", "location": "null", "lat": "37.576659035885", "lng": "127.0615676888", "useTime": "24\uc2dc\uac04 \uc774\uc6a9\uac00\ub2a5", "busiId": "PI", "bnm": "\ucc28\uc9c0\ube44", "busiNm": "\ucc28\uc9c0\ube44", "busiCall": "1600-4047", "stat": "2", "statUpdDt": "20220708005058", "lastTsdt": "20220706221049", "lastTedt": "20220706201140", "nowTsdt": "20220706221049", "powerType": null, "output": null, "method": null, "zcode": "11", "zscode": "11230", "kind": "H0", "kindDetail": "H001", "parkingFree": "Y", "note": null, "limitYn": "Y", "limitDetail": "\uac70\uc8fc\uc790\uc678 \ucd9c\uc785\uc81c\ud55c", "delYn": "N", "delDetail": null}, {"statNm": "\uc11c\uc6b8\uc2dc \ub3d9\ub300\ubb38\uad6c \uc804\ub18dSK\uc544\ud30c\ud2b8", "statId": "PI200382", "chgerId": "04", "chgerType": "02", "addr": "\uc11c\uc6b8\ud2b9\ubcc4\uc2dc \ub3d9\ub300\ubb38\uad6c \uc0ac\uac00\uc815\ub85c 148", "location": "null", "lat": "37.576659035885", "lng": "127.0615676888", "useTime": "24\uc2dc\uac04 \uc774\uc6a9\uac00\ub2a5", "busiId": "PI", "bnm": "\ucc28\uc9c0\ube44", "busiNm": "\ucc28\uc9c0\ube44", "busiCall": "1600-4047", "stat": "2", "statUpdDt": "20220707205133", "lastTsdt": "20220706231039", "lastTedt": "20220706151228", "nowTsdt": "20220706231039", "powerType": null, "output": null, "method": null, "zcode": "11", "zscode": "11230", "kind": "H0", "kindDetail": "H001", "parkingFree": "Y", "note": null, "limitYn": "Y", "limitDetail": "\uac70\uc8fc\uc790\uc678 \ucd9c\uc785\uc81c\ud55c", "delYn": "N", "delDetail": null}, {"statNm": "\uc11c\uc6b8\uc2dc \ub3d9\ub300\ubb38\uad6c \uc804\ub18dSK\uc544\ud30c\ud2b8", "statId": "PI200382", "chgerId": "05", "chgerType": "02", "addr": "\uc11c\uc6b8\ud2b9\ubcc4\uc2dc \ub3d9\ub300\ubb38\uad6c \uc0ac\uac00\uc815\ub85c 148", "location": "null", "lat": "37.576659035885", "lng": "127.0615676888", "useTime": "24\uc2dc\uac04 \uc774\uc6a9\uac00\ub2a5", "busiId": "PI", "bnm": "\ucc28\uc9c0\ube44", "busiNm": "\ucc28\uc9c0\ube44", "busiCall": "1600-4047", "stat": "2", "statUpdDt": "20220706042616", "lastTsdt": "20220604045656", "lastTedt": "20220614110818", "nowTsdt": "20220604045656", "powerType": null, "output": null, "method": null, "zcode": "11", "zscode": "11230", "kind": "H0", "kindDetail": "H001", "parkingFree": "Y", "note": null, "limitYn": "Y", "limitDetail": "\uac70\uc8fc\uc790\uc678 \ucd9c\uc785\uc81c\ud55c", "delYn": "N", "delDetail": null}, {"statNm": "\uc11c\uc6b8\uc2dc \ub3d9\ub300\ubb38\uad6c \uc804\ub18dSK\uc544\ud30c\ud2b8", "statId": "PI200382", "chgerId": "06", "chgerType": "02", "addr": "\uc11c\uc6b8\ud2b9\ubcc4\uc2dc \ub3d9\ub300\ubb38\uad6c \uc0ac\uac00\uc815\ub85c 148", "location": "null", "lat": "37.576659035885", "lng": "127.0615676888", "useTime": "24\uc2dc\uac04 \uc774\uc6a9\uac00\ub2a5", "busiId": "PI", "bnm": "\ucc28\uc9c0\ube44", "busiNm": "\ucc28\uc9c0\ube44", "busiCall": "1600-4047", "stat": "2", "statUpdDt": "20220705210743", "lastTsdt": "20220610003611", "lastTedt": "20220610085316", "nowTsdt": "20220610003611", "powerType": null, "output": null, "method": null, "zcode": "11", "zscode": "11230", "kind": "H0", "kindDetail": "H001", "parkingFree": "Y", "note": null, "limitYn": "Y", "limitDetail": "\uac70\uc8fc\uc790\uc678 \ucd9c\uc785\uc81c\ud55c", "delYn": "N", "delDetail": null}, {"statNm": "\uc11c\uc6b8\uc2dc \ub3d9\ub300\ubb38\uad6c \uc804\ub18dSK\uc544\ud30c\ud2b8", "statId": "PI200382", "chgerId": "07", "chgerType": "02", "addr": "\uc11c\uc6b8\ud2b9\ubcc4\uc2dc \ub3d9\ub300\ubb38\uad6c \uc0ac\uac00\uc815\ub85c 148", "location": "null", "lat": "37.576659035885", "lng": "127.0615676888", "useTime": "24\uc2dc\uac04 \uc774\uc6a9\uac00\ub2a5", "busiId": "PI", "bnm": "\ucc28\uc9c0\ube44", "busiNm": "\ucc28\uc9c0\ube44", "busiCall": "1600-4047", "stat": "2", "statUpdDt": "20220706175319", "lastTsdt": "20220616075335", "lastTedt": "20220616070429", "nowTsdt": "20220616075335", "powerType": null, "output": null, "method": null, "zcode": "11", "zscode": "11230", "kind": "H0", "kindDetail": "H001", "parkingFree": "Y", "note": null, "limitYn": "Y", "limitDetail": "\uac70\uc8fc\uc790\uc678 \ucd9c\uc785\uc81c\ud55c", "delYn": "N", "delDetail": null}, {"statNm": "\uc11c\uc6b8\uc2dc \ub3d9\ub300\ubb38\uad6c \uc804\ub18dSK\uc544\ud30c\ud2b8", "statId": "PI200382", "chgerId": "08", "chgerType": "02", "addr": "\uc11c\uc6b8\ud2b9\ubcc4\uc2dc \ub3d9\ub300\ubb38\uad6c \uc0ac\uac00\uc815\ub85c 148", "location": "null", "lat": "37.576659035885", "lng": "127.0615676888", "useTime": "24\uc2dc\uac04 \uc774\uc6a9\uac00\ub2a5", "busiId": "PI", "bnm": "\ucc28\uc9c0\ube44", "busiNm": "\ucc28\uc9c0\ube44", "busiCall": "1600-4047", "stat": "2", "statUpdDt": "20220703225133", "lastTsdt": "20220615162957", "lastTedt": "20220616063147", "nowTsdt": "20220615162957", "powerType": null, "output": null, "method": null, "zcode": "11", "zscode": "11230", "kind": "H0", "kindDetail": "H001", "parkingFree": "Y", "note": null, "limitYn": "Y", "limitDetail": "\uac70\uc8fc\uc790\uc678 \ucd9c\uc785\uc81c\ud55c", "delYn": "N", "delDetail": null}]