[{"statNm": "\ub355\uc131\uc77c\uc131\ud2b8\ub8e8\uc5d8\uc785\uc8fc\uc790\ub300\ud45c\ud68c\uc758", "statId": "PW011782", "chgerId": "02", "chgerType": "02", "addr": "\uacbd\uae30\ub3c4 \uc591\uc8fc\uc2dc \ub355\uc815\uae38 105", "location": "null", "lat": "37.842861325948", "lng": "127.0676345178", "useTime": "24\uc2dc\uac04 \uc774\uc6a9\uac00\ub2a5", "busiId": "PW", "bnm": "\ud30c\uc6cc\ud050\ube0c", "busiNm": "\ud30c\uc6cc\ud050\ube0c", "busiCall": "1833-8017", "stat": "2", "statUpdDt": "20220707140137", "lastTsdt": "20220427171217", "lastTedt": "20220427201241", "nowTsdt": "20220427171217", "powerType": null, "output": null, "method": null, "zcode": "41", "zscode": "41630", "kind": "H0", "kindDetail": "H001", "parkingFree": "Y", "note": null, "limitYn": "Y", "limitDetail": "\uac70\uc8fc\uc790\uc678 \ucd9c\uc785\uc81c\ud55c", "delYn": "N", "delDetail": null}, {"statNm": "\ub355\uc131\uc77c\uc131\ud2b8\ub8e8\uc5d8\uc785\uc8fc\uc790\ub300\ud45c\ud68c\uc758", "statId": "PW011782", "chgerId": "03", "chgerType": "02", "addr": "\uacbd\uae30\ub3c4 \uc591\uc8fc\uc2dc \ub355\uc815\uae38 105", "location": "null", "lat": "37.842861325948", "lng": "127.0676345178", "useTime": "24\uc2dc\uac04 \uc774\uc6a9\uac00\ub2a5", "busiId": "PW", "bnm": "\ud30c\uc6cc\ud050\ube0c", "busiNm": "\ud30c\uc6cc\ud050\ube0c", "busiCall": "1833-8017", "stat": "2", "statUpdDt": "20220707184531", "lastTsdt": "20220626175346", "lastTedt": "20220626225415", "nowTsdt": "20220626175346", "powerType": null, "output": null, "method": null, "zcode": "41", "zscode": "41630", "kind": "H0", "kindDetail": "H001", "parkingFree": "Y", "note": null, "limitYn": "Y", "limitDetail": "\uac70\uc8fc\uc790\uc678 \ucd9c\uc785\uc81c\ud55c", "delYn": "N", "delDetail": null}, {"statNm": "\ub355\uc131\uc77c\uc131\ud2b8\ub8e8\uc5d8\uc785\uc8fc\uc790\ub300\ud45c\ud68c\uc758", "statId": "PW011782", "chgerId": "04", "chgerType": "02", "addr": "\uacbd\uae30\ub3c4 \uc591\uc8fc\uc2dc \ub355\uc815\uae38 105", "location": "null", "lat": "37.842861325948", "lng": "127.0676345178", "useTime": "24\uc2dc\uac04 \uc774\uc6a9\uac00\ub2a5", "busiId": "PW", "bnm": "\ud30c\uc6cc\ud050\ube0c", "busiNm": "\ud30c\uc6cc\ud050\ube0c", "busiCall": "1833-8017", "stat": "2", "statUpdDt": "20220708113048", "lastTsdt": "20220706193318", "lastTedt": "20220706221843", "nowTsdt": "20220706193318", "powerType": null, "output": null, "method": null, "zcode": "41", "zscode": "41630", "kind": "H0", "kindDetail": "H001", "parkingFree": "Y", "note": null, "limitYn": "Y", "limitDetail": "\uac70\uc8fc\uc790\uc678 \ucd9c\uc785\uc81c\ud55c", "delYn": "N", "delDetail": null}, {"statNm": "\ub355\uc131\uc77c\uc131\ud2b8\ub8e8\uc5d8\uc785\uc8fc\uc790\ub300\ud45c\ud68c\uc758", "statId": "PW011782", "chgerId": "05", "chgerType": "02", "addr": "\uacbd\uae30\ub3c4 \uc591\uc8fc\uc2dc \ub355\uc815\uae38 105", "location": "null", "lat": "37.842861325948", "lng": "127.0676345178", "useTime": "24\uc2dc\uac04 \uc774\uc6a9\uac00\ub2a5", "busiId": "PW", "bnm": "\ud30c\uc6cc\ud050\ube0c", "busiNm": "\ud30c\uc6cc\ud050\ube0c", "busiCall": "1833-8017", "stat": "2", "statUpdDt": "20220707180046", "lastTsdt": "20220331203918", "lastTedt": "20220401023950", "nowTsdt": "20220331203918", "powerType": null, "output": null, "method": null, "zcode": "41", "zscode": "41630", "kind": "H0", "kindDetail": "H001", "parkingFree": "Y", "note": null, "limitYn": "Y", "limitDetail": "\uac70\uc8fc\uc790\uc678 \ucd9c\uc785\uc81c\ud55c", "delYn": "N", "delDetail": null}]